{
  "type": "FeatureCollection",
  "features": [
    {
      "type": "Feature",
      "properties": {
        "dep_id": 10057190,
        "url": "https://mrdata.usgs.gov/mrds/show-mrds.php?dep_id=10057190",
        "mrds_id": "TC01680",
        "mas_id": null,
        "site_name": "El Brujo Mine",
        "latitude": 14.4167,
        "longitude": -89.4445,
        "region": null,
        "country": "El Salvador",
        "state": "Santa Ana",
        "county": null,
        "com_type": "M",
        "commod1": "Iron, Copper",
        "commod2": null,
        "commod3": null,
        "oper_type": "Unknown",
        "dep_type": null,
        "prod_size": "Y",
        "dev_stat": "Past Producer",
        "ore": "Copper, Magnetite",
        "gangue": "Calcite, Epidote, Garnet",
        "other_matl": null,
        "orebody_fm": null,
        "work_type": null,
        "model": "62: Skarn Fe",
        "alteration": null,
        "conc_proc": null,
        "names": null,
        "ore_ctrl": null,
        "reporter": "Page, Norman J.",
        "hrock_unit": "Metapan Formation",
        "hrock_type": "Limestone",
        "arock_unit": null,
        "arock_type": "Diorite",
        "structure": null,
        "tectonic": null,
        "ref": "ROBERTS, R.J., AND IRVING, E.M., 1957, MINERAL DEPOSITS OF CENTRAL AMERICA:  U.S. GEOLOGICAL SURVEY BULLETIN 1034, P. 77CIMRIROBERTS AND IRVING, 1957.",
        "yfp_ba": null,
        "yr_fst_prd": null,
        "ylp_ba": null,
        "yr_lst_prd": null,
        "dy_ba": null,
        "disc_yr": 1673.0,
        "prod_yrs": null,
        "discr": null
      },
      "geometry": {
        "type": "Point",
        "coordinates": [
          -89.4445,
          14.4167
        ]
      }
    },
    {
      "type": "Feature",
      "properties": {
        "dep_id": 10057191,
        "url": "https://mrdata.usgs.gov/mrds/show-mrds.php?dep_id=10057191",
        "mrds_id": "TC01681",
        "mas_id": null,
        "site_name": "El Carmen",
        "latitude": 14.38254,
        "longitude": -89.44478,
        "region": null,
        "country": "El Salvador",
        "state": "Santa Ana",
        "county": null,
        "com_type": "M",
        "commod1": "Copper",
        "commod2": null,
        "commod3": null,
        "oper_type": "Unknown",
        "dep_type": "Vein",
        "prod_size": "N",
        "dev_stat": "Occurrence",
        "ore": "Copper",
        "gangue": null,
        "other_matl": null,
        "orebody_fm": null,
        "work_type": null,
        "model": null,
        "alteration": null,
        "conc_proc": null,
        "names": null,
        "ore_ctrl": null,
        "reporter": "Page, Norman J.",
        "hrock_unit": null,
        "hrock_type": "Conglomerate",
        "arock_unit": null,
        "arock_type": null,
        "structure": null,
        "tectonic": null,
        "ref": "ROBERTS, R.J., AND IRVING, E.M., 1957, MINERAL DEPOSITS OF CENTRAL AMERICA:  U.S. GEOLOGICAL SURVEY BULLETIN 1034, P. 77-78CIMRIROBERTS AND IRVING, 1957.",
        "yfp_ba": null,
        "yr_fst_prd": null,
        "ylp_ba": null,
        "yr_lst_prd": null,
        "dy_ba": null,
        "disc_yr": null,
        "prod_yrs": null,
        "discr": null
      },
      "geometry": {
        "type": "Point",
        "coordinates": [
          -89.44478,
          14.38254
        ]
      }
    },
    {
      "type": "Feature",
      "properties": {
        "dep_id": 10057192,
        "url": "https://mrdata.usgs.gov/mrds/show-mrds.php?dep_id=10057192",
        "mrds_id": "TC01682",
        "mas_id": null,
        "site_name": "Monte Verde Deposit",
        "latitude": 14.30504,
        "longitude": -89.04338,
        "region": null,
        "country": "El Salvador",
        "state": "Santa Ana",
        "county": null,
        "com_type": "M",
        "commod1": "Copper",
        "commod2": null,
        "commod3": null,
        "oper_type": "Unknown",
        "dep_type": null,
        "prod_size": "N",
        "dev_stat": "Occurrence",
        "ore": "Copper",
        "gangue": "Calcite, Epidote, Garnet, Quartz",
        "other_matl": null,
        "orebody_fm": null,
        "work_type": null,
        "model": null,
        "alteration": null,
        "conc_proc": null,
        "names": null,
        "ore_ctrl": null,
        "reporter": "Page, Norman J.",
        "hrock_unit": null,
        "hrock_type": null,
        "arock_unit": null,
        "arock_type": null,
        "structure": null,
        "tectonic": null,
        "ref": "ROBERTS, R.J., AND IRVING, E.M., 1957, MINERAL DEPOSITS OF CENTRAL AMERICA:  U.S. GEOLOGICAL SURVEY BULLETIN 1034, P. 78CIMRIROBERTS AND IRVING, 1957.",
        "yfp_ba": null,
        "yr_fst_prd": null,
        "ylp_ba": null,
        "yr_lst_prd": null,
        "dy_ba": null,
        "disc_yr": null,
        "prod_yrs": null,
        "discr": null
      },
      "geometry": {
        "type": "Point",
        "coordinates": [
          -89.04338,
          14.30504
        ]
      }
    },
    {
      "type": "Feature",
      "properties": {
        "dep_id": 10057193,
        "url": "https://mrdata.usgs.gov/mrds/show-mrds.php?dep_id=10057193",
        "mrds_id": "TC01683",
        "mas_id": null,
        "site_name": "Chaguite Deposits",
        "latitude": 14.40643,
        "longitude": -89.43062,
        "region": null,
        "country": "El Salvador",
        "state": "Santa Ana",
        "county": null,
        "com_type": "M",
        "commod1": "Copper",
        "commod2": null,
        "commod3": null,
        "oper_type": "Unknown",
        "dep_type": null,
        "prod_size": "N",
        "dev_stat": "Occurrence",
        "ore": "Chalcocite, Copper",
        "gangue": "Calcite",
        "other_matl": null,
        "orebody_fm": null,
        "work_type": null,
        "model": null,
        "alteration": null,
        "conc_proc": null,
        "names": null,
        "ore_ctrl": null,
        "reporter": "Page, Norman J.",
        "hrock_unit": null,
        "hrock_type": "Sandstone,Andesite",
        "arock_unit": null,
        "arock_type": null,
        "structure": null,
        "tectonic": null,
        "ref": "ROBERTS, R.J., AND IRVING, E.M., 1957, MINERAL DEPOSITS OF CENTRAL AMERICA:  U.S. GEOLOGICAL SURVEY BULLETIN 1034, P. 77CIMRI",
        "yfp_ba": null,
        "yr_fst_prd": null,
        "ylp_ba": null,
        "yr_lst_prd": null,
        "dy_ba": null,
        "disc_yr": null,
        "prod_yrs": null,
        "discr": null
      },
      "geometry": {
        "type": "Point",
        "coordinates": [
          -89.43062,
          14.40643
        ]
      }
    },
    {
      "type": "Feature",
      "properties": {
        "dep_id": 10057194,
        "url": "https://mrdata.usgs.gov/mrds/show-mrds.php?dep_id=10057194",
        "mrds_id": "TC01684",
        "mas_id": null,
        "site_name": "La Esperanza Prospect",
        "latitude": 14.34143,
        "longitude": -89.46312,
        "region": null,
        "country": "El Salvador",
        "state": "Santa Ana",
        "county": null,
        "com_type": "M",
        "commod1": "Lead",
        "commod2": null,
        "commod3": null,
        "oper_type": "Unknown",
        "dep_type": null,
        "prod_size": "N",
        "dev_stat": "Occurrence",
        "ore": "Anglesite, Galena",
        "gangue": null,
        "other_matl": null,
        "orebody_fm": null,
        "work_type": null,
        "model": null,
        "alteration": null,
        "conc_proc": null,
        "names": null,
        "ore_ctrl": null,
        "reporter": "Page, Norman J.",
        "hrock_unit": "Metapan Formation",
        "hrock_type": "Limestone",
        "arock_unit": null,
        "arock_type": "Granite",
        "structure": null,
        "tectonic": null,
        "ref": "ROBERTS, R.J., AND IRVING, E.M., 1957, MINERAL DEPOSITS OF CENTRAL AMERICA:  U.S. GEOLOGICAL SURVEY BULLETIN 1034, P. 77CIMRI",
        "yfp_ba": null,
        "yr_fst_prd": null,
        "ylp_ba": null,
        "yr_lst_prd": null,
        "dy_ba": null,
        "disc_yr": null,
        "prod_yrs": null,
        "discr": null
      },
      "geometry": {
        "type": "Point",
        "coordinates": [
          -89.46312,
          14.34143
        ]
      }
    },
    {
      "type": "Feature",
      "properties": {
        "dep_id": 10057195,
        "url": "https://mrdata.usgs.gov/mrds/show-mrds.php?dep_id=10057195",
        "mrds_id": "TC01685",
        "mas_id": null,
        "site_name": "San Isidro Montanita Prospect",
        "latitude": 14.34143,
        "longitude": -89.46256,
        "region": null,
        "country": "El Salvador",
        "state": "Santa Ana",
        "county": null,
        "com_type": "M",
        "commod1": "Lead, Copper",
        "commod2": null,
        "commod3": null,
        "oper_type": "Unknown",
        "dep_type": "Vein",
        "prod_size": "N",
        "dev_stat": "Occurrence",
        "ore": "Chalcopyrite, Galena, Pyrite",
        "gangue": null,
        "other_matl": null,
        "orebody_fm": null,
        "work_type": null,
        "model": null,
        "alteration": null,
        "conc_proc": null,
        "names": null,
        "ore_ctrl": null,
        "reporter": "Page, Norman J.",
        "hrock_unit": null,
        "hrock_type": "Diorite",
        "arock_unit": null,
        "arock_type": null,
        "structure": null,
        "tectonic": null,
        "ref": "ROBERTS, R.J., AND IRVING, E.M., 1957, MINERAL DEPOSITS OF CENTRAL AMERICA:  U.S. GEOLOGICAL SURVEY BULLETIN 1034, P. 77CIMRI",
        "yfp_ba": null,
        "yr_fst_prd": null,
        "ylp_ba": null,
        "yr_lst_prd": null,
        "dy_ba": null,
        "disc_yr": null,
        "prod_yrs": null,
        "discr": null
      },
      "geometry": {
        "type": "Point",
        "coordinates": [
          -89.46256,
          14.34143
        ]
      }
    },
    {
      "type": "Feature",
      "properties": {
        "dep_id": 10057196,
        "url": "https://mrdata.usgs.gov/mrds/show-mrds.php?dep_id=10057196",
        "mrds_id": "TC01686",
        "mas_id": null,
        "site_name": "Unnamed San Isidro Copper Prospect",
        "latitude": 14.33865,
        "longitude": -89.48617,
        "region": null,
        "country": "El Salvador",
        "state": "Santa Ana",
        "county": null,
        "com_type": "M",
        "commod1": "Copper",
        "commod2": null,
        "commod3": null,
        "oper_type": "Unknown",
        "dep_type": null,
        "prod_size": "N",
        "dev_stat": "Occurrence",
        "ore": "Copper",
        "gangue": null,
        "other_matl": null,
        "orebody_fm": null,
        "work_type": null,
        "model": null,
        "alteration": null,
        "conc_proc": null,
        "names": null,
        "ore_ctrl": null,
        "reporter": "Page, Norman J.",
        "hrock_unit": null,
        "hrock_type": null,
        "arock_unit": null,
        "arock_type": null,
        "structure": null,
        "tectonic": null,
        "ref": "ROBERTS, R.J., AND IRVING, E.M., 1957, MINERAL DEPOSITS OF CENTRAL AMERICA:  U.S. GEOLOGICAL SURVEY BULLETIN 1034, P. 77CIMRI",
        "yfp_ba": null,
        "yr_fst_prd": null,
        "ylp_ba": null,
        "yr_lst_prd": null,
        "dy_ba": null,
        "disc_yr": null,
        "prod_yrs": null,
        "discr": null
      },
      "geometry": {
        "type": "Point",
        "coordinates": [
          -89.48617,
          14.33865
        ]
      }
    },
    {
      "type": "Feature",
      "properties": {
        "dep_id": 10057197,
        "url": "https://mrdata.usgs.gov/mrds/show-mrds.php?dep_id=10057197",
        "mrds_id": "TC01687",
        "mas_id": null,
        "site_name": "El Tajado Mine",
        "latitude": 14.41115,
        "longitude": -89.43589,
        "region": null,
        "country": "El Salvador",
        "state": "Santa Ana",
        "county": null,
        "com_type": "M",
        "commod1": "Iron, Copper, Zinc",
        "commod2": null,
        "commod3": null,
        "oper_type": "Unknown",
        "dep_type": null,
        "prod_size": "N",
        "dev_stat": "Occurrence",
        "ore": "Calamine, Magnetite, Specularite, Sphalerite",
        "gangue": "Garnet",
        "other_matl": null,
        "orebody_fm": null,
        "work_type": null,
        "model": null,
        "alteration": null,
        "conc_proc": null,
        "names": null,
        "ore_ctrl": null,
        "reporter": "Page, Norman J.",
        "hrock_unit": "Metapan Formation",
        "hrock_type": "Limestone",
        "arock_unit": null,
        "arock_type": "Diorite",
        "structure": null,
        "tectonic": null,
        "ref": "ROBERTS, R.J., AND IRVING, E.M., 1957, MINERAL DEPOSITS OF CENTRAL AMERICA:  U.S. GEOLOGICAL SURVEY BULLETIN 1034, P. 76-77CIMRI",
        "yfp_ba": null,
        "yr_fst_prd": null,
        "ylp_ba": null,
        "yr_lst_prd": null,
        "dy_ba": null,
        "disc_yr": null,
        "prod_yrs": null,
        "discr": null
      },
      "geometry": {
        "type": "Point",
        "coordinates": [
          -89.43589,
          14.41115
        ]
      }
    },
    {
      "type": "Feature",
      "properties": {
        "dep_id": 10057198,
        "url": "https://mrdata.usgs.gov/mrds/show-mrds.php?dep_id=10057198",
        "mrds_id": "TC01688",
        "mas_id": null,
        "site_name": "San Casimiro Mine",
        "latitude": 14.3342,
        "longitude": -89.50006,
        "region": null,
        "country": "El Salvador",
        "state": "Santa Ana",
        "county": null,
        "com_type": "M",
        "commod1": "Gold, Zinc, Lead, Silver",
        "commod2": null,
        "commod3": null,
        "oper_type": "Unknown",
        "dep_type": null,
        "prod_size": "N",
        "dev_stat": "Occurrence",
        "ore": "Chalcopyrite, Galena, Pyrite, Sphalerite",
        "gangue": null,
        "other_matl": null,
        "orebody_fm": "VEINLETS, POCKETS, LENSES, DISSEMINATED",
        "work_type": null,
        "model": "60: Skarn Zn-Pb",
        "alteration": "Silicification",
        "conc_proc": null,
        "names": null,
        "ore_ctrl": null,
        "reporter": "Page, Norman J.",
        "hrock_unit": "Metapan Formation",
        "hrock_type": "Hornfels,Limestone",
        "arock_unit": null,
        "arock_type": null,
        "structure": null,
        "tectonic": null,
        "ref": "ROBERTS, R.J., AND IRVING, E.M., 1957, MINERAL DEPOSITS OF CENTRAL AMERICA:  U.S. GEOLOGICAL SURVEY BULLETIN 1034, P. 76CIMRIROBERTS AND IRVING, 1957.",
        "yfp_ba": null,
        "yr_fst_prd": null,
        "ylp_ba": null,
        "yr_lst_prd": null,
        "dy_ba": null,
        "disc_yr": null,
        "prod_yrs": null,
        "discr": null
      },
      "geometry": {
        "type": "Point",
        "coordinates": [
          -89.50006,
          14.3342
        ]
      }
    },
    {
      "type": "Feature",
      "properties": {
        "dep_id": 10057199,
        "url": "https://mrdata.usgs.gov/mrds/show-mrds.php?dep_id=10057199",
        "mrds_id": "TC01689",
        "mas_id": null,
        "site_name": "Occurrence At Quabrada Del Tigre",
        "latitude": 14.36615,
        "longitude": -89.44923,
        "region": null,
        "country": "El Salvador",
        "state": "Santa Ana",
        "county": null,
        "com_type": "M",
        "commod1": "Lead",
        "commod2": null,
        "commod3": null,
        "oper_type": "Unknown",
        "dep_type": null,
        "prod_size": "N",
        "dev_stat": "Occurrence",
        "ore": "Galena, Pyrite",
        "gangue": null,
        "other_matl": null,
        "orebody_fm": null,
        "work_type": null,
        "model": null,
        "alteration": null,
        "conc_proc": null,
        "names": null,
        "ore_ctrl": null,
        "reporter": "Page, Norman J.",
        "hrock_unit": null,
        "hrock_type": "Argillite",
        "arock_unit": null,
        "arock_type": null,
        "structure": null,
        "tectonic": null,
        "ref": "ROBERTS, R.J., AND IRVING, E.M., 1957, MINERAL DEPOSITS OF CENTRAL AMERICA:  U.S. GEOLOGICAL SURVEY BULLETIN 1034, P. 78CIMRI",
        "yfp_ba": null,
        "yr_fst_prd": null,
        "ylp_ba": null,
        "yr_lst_prd": null,
        "dy_ba": null,
        "disc_yr": null,
        "prod_yrs": null,
        "discr": null
      },
      "geometry": {
        "type": "Point",
        "coordinates": [
          -89.44923,
          14.36615
        ]
      }
    },
    {
      "type": "Feature",
      "properties": {
        "dep_id": 10057200,
        "url": "https://mrdata.usgs.gov/mrds/show-mrds.php?dep_id=10057200",
        "mrds_id": "TC01690",
        "mas_id": null,
        "site_name": "Occurrence At San Rafael",
        "latitude": 14.3342,
        "longitude": -89.4445,
        "region": null,
        "country": "El Salvador",
        "state": "Santa Ana",
        "county": null,
        "com_type": "M",
        "commod1": "Sulfur-Pyrite",
        "commod2": null,
        "commod3": null,
        "oper_type": "Unknown",
        "dep_type": null,
        "prod_size": "N",
        "dev_stat": "Occurrence",
        "ore": "Pyrite",
        "gangue": null,
        "other_matl": null,
        "orebody_fm": null,
        "work_type": null,
        "model": null,
        "alteration": null,
        "conc_proc": null,
        "names": null,
        "ore_ctrl": null,
        "reporter": "Page, Norman J.",
        "hrock_unit": null,
        "hrock_type": "Shale",
        "arock_unit": null,
        "arock_type": null,
        "structure": null,
        "tectonic": null,
        "ref": "ROBERTS, R.J., AND IRVING, E.M., 1957, MINERAL DEPOSITS OF CENTRAL AMERICA:  U.S. GEOLOGICAL SURVEY BULLETIN 1034, P. 78CIMRI",
        "yfp_ba": null,
        "yr_fst_prd": null,
        "ylp_ba": null,
        "yr_lst_prd": null,
        "dy_ba": null,
        "disc_yr": null,
        "prod_yrs": null,
        "discr": null
      },
      "geometry": {
        "type": "Point",
        "coordinates": [
          -89.4445,
          14.3342
        ]
      }
    },
    {
      "type": "Feature",
      "properties": {
        "dep_id": 10057201,
        "url": "https://mrdata.usgs.gov/mrds/show-mrds.php?dep_id=10057201",
        "mrds_id": "TC01691",
        "mas_id": null,
        "site_name": "Occurrence At Canas Dulces",
        "latitude": 14.36754,
        "longitude": -89.31673,
        "region": null,
        "country": "El Salvador",
        "state": "Santa Ana",
        "county": null,
        "com_type": "M",
        "commod1": "Sulfur-Pyrite",
        "commod2": null,
        "commod3": null,
        "oper_type": "Unknown",
        "dep_type": null,
        "prod_size": "N",
        "dev_stat": "Occurrence",
        "ore": "Pyrite",
        "gangue": null,
        "other_matl": null,
        "orebody_fm": null,
        "work_type": null,
        "model": null,
        "alteration": null,
        "conc_proc": null,
        "names": null,
        "ore_ctrl": null,
        "reporter": "Page, Norman J.",
        "hrock_unit": null,
        "hrock_type": "Argillite",
        "arock_unit": null,
        "arock_type": null,
        "structure": null,
        "tectonic": null,
        "ref": "ROBERTS, R.J., AND IRVING, E.M., 1957, MINERAL DEPOSITS OF CENTRAL AMERICA:  U.S. GEOLOGICAL SURVEY BULLETIN 1034, P. 78CIMRI",
        "yfp_ba": null,
        "yr_fst_prd": null,
        "ylp_ba": null,
        "yr_lst_prd": null,
        "dy_ba": null,
        "disc_yr": null,
        "prod_yrs": null,
        "discr": null
      },
      "geometry": {
        "type": "Point",
        "coordinates": [
          -89.31673,
          14.36754
        ]
      }
    },
    {
      "type": "Feature",
      "properties": {
        "dep_id": 10057202,
        "url": "https://mrdata.usgs.gov/mrds/show-mrds.php?dep_id=10057202",
        "mrds_id": "TC01692",
        "mas_id": null,
        "site_name": "Cerro El Cobano",
        "latitude": 14.10644,
        "longitude": -89.46617,
        "region": null,
        "country": "El Salvador",
        "state": null,
        "county": null,
        "com_type": "N",
        "commod1": "Perlite",
        "commod2": null,
        "commod3": null,
        "oper_type": "Unknown",
        "dep_type": null,
        "prod_size": "N",
        "dev_stat": "Occurrence",
        "ore": null,
        "gangue": null,
        "other_matl": null,
        "orebody_fm": null,
        "work_type": null,
        "model": null,
        "alteration": null,
        "conc_proc": null,
        "names": null,
        "ore_ctrl": null,
        "reporter": "Page, Norman J.",
        "hrock_unit": null,
        "hrock_type": "Felsic Volcanic Rock",
        "arock_unit": null,
        "arock_type": null,
        "structure": null,
        "tectonic": null,
        "ref": "LORENZ, W., AND MULLER, P., 1982, PERLITE IN EL SALVADOR, CENTRAL AMERICA:  NEW MEXICO BUREAU OF MINES AND MINERAL RESOURCES CIRCULAR 182, P. 103-107CIMRI",
        "yfp_ba": null,
        "yr_fst_prd": null,
        "ylp_ba": null,
        "yr_lst_prd": null,
        "dy_ba": null,
        "disc_yr": null,
        "prod_yrs": null,
        "discr": null
      },
      "geometry": {
        "type": "Point",
        "coordinates": [
          -89.46617,
          14.10644
        ]
      }
    },
    {
      "type": "Feature",
      "properties": {
        "dep_id": 10057203,
        "url": "https://mrdata.usgs.gov/mrds/show-mrds.php?dep_id=10057203",
        "mrds_id": "TC01693",
        "mas_id": null,
        "site_name": "San Ignacio",
        "latitude": 14.33865,
        "longitude": -89.16783,
        "region": null,
        "country": "El Salvador",
        "state": null,
        "county": null,
        "com_type": "N",
        "commod1": "Perlite",
        "commod2": null,
        "commod3": null,
        "oper_type": "Unknown",
        "dep_type": null,
        "prod_size": "N",
        "dev_stat": "Occurrence",
        "ore": null,
        "gangue": null,
        "other_matl": null,
        "orebody_fm": null,
        "work_type": null,
        "model": null,
        "alteration": null,
        "conc_proc": null,
        "names": null,
        "ore_ctrl": null,
        "reporter": "Page, Norman J.",
        "hrock_unit": null,
        "hrock_type": "Felsic Volcanic Rock",
        "arock_unit": null,
        "arock_type": null,
        "structure": null,
        "tectonic": null,
        "ref": "LORENZ, W., AND MULLER, P., 1982, PERLITE IN EL SALVADOR, CENTRAL AMERICA:  NEW MEXICO BUREAU OF MINES AND MINERAL RESOURCES CIRCULAR 182, P. 103-107CIMRI",
        "yfp_ba": null,
        "yr_fst_prd": null,
        "ylp_ba": null,
        "yr_lst_prd": null,
        "dy_ba": null,
        "disc_yr": null,
        "prod_yrs": null,
        "discr": null
      },
      "geometry": {
        "type": "Point",
        "coordinates": [
          -89.16783,
          14.33865
        ]
      }
    },
    {
      "type": "Feature",
      "properties": {
        "dep_id": 10057204,
        "url": "https://mrdata.usgs.gov/mrds/show-mrds.php?dep_id=10057204",
        "mrds_id": "TC01694",
        "mas_id": null,
        "site_name": "San Francisco Gotera",
        "latitude": 13.70007,
        "longitude": -88.10642,
        "region": null,
        "country": "El Salvador",
        "state": null,
        "county": null,
        "com_type": "N",
        "commod1": "Perlite",
        "commod2": null,
        "commod3": null,
        "oper_type": "Unknown",
        "dep_type": null,
        "prod_size": "N",
        "dev_stat": "Occurrence",
        "ore": null,
        "gangue": null,
        "other_matl": null,
        "orebody_fm": null,
        "work_type": null,
        "model": null,
        "alteration": null,
        "conc_proc": null,
        "names": null,
        "ore_ctrl": null,
        "reporter": "Page, Norman J.",
        "hrock_unit": null,
        "hrock_type": "Felsic Volcanic Rock",
        "arock_unit": null,
        "arock_type": null,
        "structure": null,
        "tectonic": null,
        "ref": "LORENZ, W., AND MULLER, P., 1982, PERLITE IN EL SALVADOR, CENTRAL AMERICA:  NEW MEXICO BUREAU OF MINES AND MINERAL RESOURCES CIRCULAR 182, P. 103-107CIMRI",
        "yfp_ba": null,
        "yr_fst_prd": null,
        "ylp_ba": null,
        "yr_lst_prd": null,
        "dy_ba": null,
        "disc_yr": null,
        "prod_yrs": null,
        "discr": null
      },
      "geometry": {
        "type": "Point",
        "coordinates": [
          -88.10642,
          13.70007
        ]
      }
    },
    {
      "type": "Feature",
      "properties": {
        "dep_id": 10057205,
        "url": "https://mrdata.usgs.gov/mrds/show-mrds.php?dep_id=10057205",
        "mrds_id": "TC01695",
        "mas_id": null,
        "site_name": "El Triunfo",
        "latitude": 13.66757,
        "longitude": -88.09641,
        "region": null,
        "country": "El Salvador",
        "state": null,
        "county": null,
        "com_type": "N",
        "commod1": "Perlite",
        "commod2": null,
        "commod3": null,
        "oper_type": "Unknown",
        "dep_type": null,
        "prod_size": "N",
        "dev_stat": "Occurrence",
        "ore": null,
        "gangue": null,
        "other_matl": null,
        "orebody_fm": null,
        "work_type": null,
        "model": null,
        "alteration": null,
        "conc_proc": null,
        "names": null,
        "ore_ctrl": null,
        "reporter": "Page, Norman J.",
        "hrock_unit": null,
        "hrock_type": "Felsic Volcanic Rock",
        "arock_unit": null,
        "arock_type": null,
        "structure": null,
        "tectonic": null,
        "ref": "LORENZ, W., AND MULLER, P., 1982, PERLITE IN EL SALVADOR, CENTRAL AMERICA:  NEW MEXICO BUREAU OF MINES AND MINERAL RESOURCES CIRCULAR 182, P. 103-107CIMRI",
        "yfp_ba": null,
        "yr_fst_prd": null,
        "ylp_ba": null,
        "yr_lst_prd": null,
        "dy_ba": null,
        "disc_yr": null,
        "prod_yrs": null,
        "discr": null
      },
      "geometry": {
        "type": "Point",
        "coordinates": [
          -88.09641,
          13.66757
        ]
      }
    },
    {
      "type": "Feature",
      "properties": {
        "dep_id": 10057206,
        "url": "https://mrdata.usgs.gov/mrds/show-mrds.php?dep_id=10057206",
        "mrds_id": "TC01696",
        "mas_id": null,
        "site_name": "Agua Zarca",
        "latitude": 13.53285,
        "longitude": -88.19447,
        "region": null,
        "country": "El Salvador",
        "state": null,
        "county": null,
        "com_type": "N",
        "commod1": "Perlite",
        "commod2": null,
        "commod3": null,
        "oper_type": "Unknown",
        "dep_type": null,
        "prod_size": "N",
        "dev_stat": "Occurrence",
        "ore": null,
        "gangue": null,
        "other_matl": null,
        "orebody_fm": null,
        "work_type": null,
        "model": null,
        "alteration": null,
        "conc_proc": null,
        "names": null,
        "ore_ctrl": null,
        "reporter": "Page, Norman J.",
        "hrock_unit": null,
        "hrock_type": "Felsic Volcanic Rock",
        "arock_unit": null,
        "arock_type": null,
        "structure": null,
        "tectonic": null,
        "ref": "LORENZ, W., AND MULLER, P., 1982, PERLITE IN EL SALVADOR, CENTRAL AMERICA:  NEW MEXICO BUREAU OF MINES AND MINERAL RESOURCES CIRCULAR 182, P. 103-107CIMRI",
        "yfp_ba": null,
        "yr_fst_prd": null,
        "ylp_ba": null,
        "yr_lst_prd": null,
        "dy_ba": null,
        "disc_yr": null,
        "prod_yrs": null,
        "discr": null
      },
      "geometry": {
        "type": "Point",
        "coordinates": [
          -88.19447,
          13.53285
        ]
      }
    },
    {
      "type": "Feature",
      "properties": {
        "dep_id": 10057207,
        "url": "https://mrdata.usgs.gov/mrds/show-mrds.php?dep_id=10057207",
        "mrds_id": "TC01697",
        "mas_id": null,
        "site_name": "Cerro El Carmen",
        "latitude": 13.63174,
        "longitude": -89.01199,
        "region": null,
        "country": "El Salvador",
        "state": null,
        "county": null,
        "com_type": "N",
        "commod1": "Perlite",
        "commod2": null,
        "commod3": null,
        "oper_type": "Unknown",
        "dep_type": null,
        "prod_size": "N",
        "dev_stat": "Occurrence",
        "ore": null,
        "gangue": null,
        "other_matl": null,
        "orebody_fm": null,
        "work_type": null,
        "model": null,
        "alteration": null,
        "conc_proc": null,
        "names": null,
        "ore_ctrl": null,
        "reporter": "Page, Norman J.",
        "hrock_unit": null,
        "hrock_type": "Felsic Volcanic Rock",
        "arock_unit": null,
        "arock_type": null,
        "structure": null,
        "tectonic": null,
        "ref": "LORENZ, W., AND MULLER, P., 1982, PERLITE IN EL SALVADOR, CENTRAL AMERICA:  NEW MEXICO BUREAU OF MINES AND MINERAL RESOURCES CIRCULAR 182, P. 103-107CIMRI",
        "yfp_ba": null,
        "yr_fst_prd": null,
        "ylp_ba": null,
        "yr_lst_prd": null,
        "dy_ba": null,
        "disc_yr": null,
        "prod_yrs": null,
        "discr": null
      },
      "geometry": {
        "type": "Point",
        "coordinates": [
          -89.01199,
          13.63174
        ]
      }
    },
    {
      "type": "Feature",
      "properties": {
        "dep_id": 10057208,
        "url": "https://mrdata.usgs.gov/mrds/show-mrds.php?dep_id=10057208",
        "mrds_id": "TC01698",
        "mas_id": null,
        "site_name": "El Carmen",
        "latitude": 13.72701,
        "longitude": -88.89811,
        "region": null,
        "country": "El Salvador",
        "state": null,
        "county": null,
        "com_type": "N",
        "commod1": "Perlite",
        "commod2": null,
        "commod3": null,
        "oper_type": "Unknown",
        "dep_type": null,
        "prod_size": "N",
        "dev_stat": "Occurrence",
        "ore": null,
        "gangue": null,
        "other_matl": null,
        "orebody_fm": null,
        "work_type": null,
        "model": null,
        "alteration": null,
        "conc_proc": null,
        "names": null,
        "ore_ctrl": null,
        "reporter": "Page, Norman J.",
        "hrock_unit": null,
        "hrock_type": "Felsic Volcanic Rock",
        "arock_unit": null,
        "arock_type": null,
        "structure": null,
        "tectonic": null,
        "ref": "LORENZ, W., AND MULLER, P., 1982, PERLITE IN EL SALVADOR, CENTRAL AMERICA:  NEW MEXICO BUREAU OF MINES AND MINERAL RESOURCES CIRCULAR 182, P. 103-107CIMRI",
        "yfp_ba": null,
        "yr_fst_prd": null,
        "ylp_ba": null,
        "yr_lst_prd": null,
        "dy_ba": null,
        "disc_yr": null,
        "prod_yrs": null,
        "discr": null
      },
      "geometry": {
        "type": "Point",
        "coordinates": [
          -88.89811,
          13.72701
        ]
      }
    },
    {
      "type": "Feature",
      "properties": {
        "dep_id": 10057209,
        "url": "https://mrdata.usgs.gov/mrds/show-mrds.php?dep_id=10057209",
        "mrds_id": "TC01699",
        "mas_id": null,
        "site_name": "Cerro Buena Vista",
        "latitude": 13.72701,
        "longitude": -89.00755,
        "region": null,
        "country": "El Salvador",
        "state": null,
        "county": null,
        "com_type": "N",
        "commod1": "Perlite",
        "commod2": null,
        "commod3": null,
        "oper_type": "Unknown",
        "dep_type": null,
        "prod_size": "N",
        "dev_stat": "Occurrence",
        "ore": null,
        "gangue": null,
        "other_matl": null,
        "orebody_fm": null,
        "work_type": null,
        "model": null,
        "alteration": null,
        "conc_proc": null,
        "names": null,
        "ore_ctrl": null,
        "reporter": "Page, Norman J.",
        "hrock_unit": null,
        "hrock_type": "Felsic Volcanic Rock",
        "arock_unit": null,
        "arock_type": null,
        "structure": null,
        "tectonic": null,
        "ref": "LORENZ, W., AND MULLER, P., 1982, PERLITE IN EL SALVADOR, CENTRAL AMERICA:  NEW MEXICO BUREAU OF MINES AND MINERAL RESOURCES CIRCULAR 182, P. 103-107CIMRI",
        "yfp_ba": null,
        "yr_fst_prd": null,
        "ylp_ba": null,
        "yr_lst_prd": null,
        "dy_ba": null,
        "disc_yr": null,
        "prod_yrs": null,
        "discr": null
      },
      "geometry": {
        "type": "Point",
        "coordinates": [
          -89.00755,
          13.72701
        ]
      }
    },
    {
      "type": "Feature",
      "properties": {
        "dep_id": 10057210,
        "url": "https://mrdata.usgs.gov/mrds/show-mrds.php?dep_id=10057210",
        "mrds_id": "TC01700",
        "mas_id": null,
        "site_name": "Venecia",
        "latitude": 13.7409,
        "longitude": -89.14533,
        "region": null,
        "country": "El Salvador",
        "state": null,
        "county": null,
        "com_type": "N",
        "commod1": "Perlite",
        "commod2": null,
        "commod3": null,
        "oper_type": "Unknown",
        "dep_type": null,
        "prod_size": "N",
        "dev_stat": "Occurrence",
        "ore": null,
        "gangue": null,
        "other_matl": null,
        "orebody_fm": null,
        "work_type": null,
        "model": null,
        "alteration": null,
        "conc_proc": null,
        "names": null,
        "ore_ctrl": null,
        "reporter": "Page, Norman J.",
        "hrock_unit": null,
        "hrock_type": "Felsic Volcanic Rock",
        "arock_unit": null,
        "arock_type": null,
        "structure": null,
        "tectonic": null,
        "ref": "LORENZ, W., AND MULLER, P., 1982, PERLITE IN EL SALVADOR, CENTRAL AMERICA:  NEW MEXICO BUREAU OF MINES AND MINERAL RESOURCES CIRCULAR 182, P. 103-107CIMRI",
        "yfp_ba": null,
        "yr_fst_prd": null,
        "ylp_ba": null,
        "yr_lst_prd": null,
        "dy_ba": null,
        "disc_yr": null,
        "prod_yrs": null,
        "discr": null
      },
      "geometry": {
        "type": "Point",
        "coordinates": [
          -89.14533,
          13.7409
        ]
      }
    },
    {
      "type": "Feature",
      "properties": {
        "dep_id": 10057211,
        "url": "https://mrdata.usgs.gov/mrds/show-mrds.php?dep_id=10057211",
        "mrds_id": "TC01701",
        "mas_id": null,
        "site_name": "El Rosario Perlite Deposit",
        "latitude": 13.77007,
        "longitude": -88.90755,
        "region": null,
        "country": "El Salvador",
        "state": "Cuscatlan",
        "county": null,
        "com_type": "N",
        "commod1": "Perlite",
        "commod2": null,
        "commod3": null,
        "oper_type": "Unknown",
        "dep_type": null,
        "prod_size": "N",
        "dev_stat": "Occurrence",
        "ore": null,
        "gangue": null,
        "other_matl": null,
        "orebody_fm": null,
        "work_type": null,
        "model": null,
        "alteration": null,
        "conc_proc": null,
        "names": null,
        "ore_ctrl": null,
        "reporter": "Page, Norman J.",
        "hrock_unit": "Cuscatlan Formation",
        "hrock_type": "Volcanic Rock (Aphanitic),Obsidian,Rhyodacite",
        "arock_unit": null,
        "arock_type": null,
        "structure": null,
        "tectonic": null,
        "ref": "LORENZ, W., AND MULLER, P., 1982, PERLITE IN EL SALVADOR, CENTRAL AMERICA:  NEW MEXICO BUREAU OF MINES AND MINERAL RESOURCES CIRCULAR 182, P. 103-107CIMRILORENZ AND MILLER, 1982.",
        "yfp_ba": null,
        "yr_fst_prd": null,
        "ylp_ba": null,
        "yr_lst_prd": null,
        "dy_ba": null,
        "disc_yr": null,
        "prod_yrs": null,
        "discr": null
      },
      "geometry": {
        "type": "Point",
        "coordinates": [
          -88.90755,
          13.77007
        ]
      }
    },
    {
      "type": "Feature",
      "properties": {
        "dep_id": 10057212,
        "url": "https://mrdata.usgs.gov/mrds/show-mrds.php?dep_id=10057212",
        "mrds_id": "TC01702",
        "mas_id": null,
        "site_name": "Ciudad Delgado",
        "latitude": 13.73729,
        "longitude": -89.16477,
        "region": null,
        "country": "El Salvador",
        "state": null,
        "county": null,
        "com_type": "N",
        "commod1": "Perlite",
        "commod2": null,
        "commod3": null,
        "oper_type": "Unknown",
        "dep_type": null,
        "prod_size": "N",
        "dev_stat": "Occurrence",
        "ore": null,
        "gangue": null,
        "other_matl": null,
        "orebody_fm": null,
        "work_type": null,
        "model": null,
        "alteration": null,
        "conc_proc": null,
        "names": null,
        "ore_ctrl": null,
        "reporter": "Page, Norman J.",
        "hrock_unit": null,
        "hrock_type": "Felsic Volcanic Rock",
        "arock_unit": null,
        "arock_type": null,
        "structure": null,
        "tectonic": null,
        "ref": "LORENZ, W., AND MULLER, P., 1982, PERLITE IN EL SALVADOR, CENTRAL AMERICA:  NEW MEXICO BUREAU OF MINES AND MINERAL RESOURCES CIRCULAR 182, P. 103-107CIMRI",
        "yfp_ba": null,
        "yr_fst_prd": null,
        "ylp_ba": null,
        "yr_lst_prd": null,
        "dy_ba": null,
        "disc_yr": null,
        "prod_yrs": null,
        "discr": null
      },
      "geometry": {
        "type": "Point",
        "coordinates": [
          -89.16477,
          13.73729
        ]
      }
    },
    {
      "type": "Feature",
      "properties": {
        "dep_id": 10057213,
        "url": "https://mrdata.usgs.gov/mrds/show-mrds.php?dep_id=10057213",
        "mrds_id": "TC01703",
        "mas_id": null,
        "site_name": "Cerro Afate",
        "latitude": 14.14671,
        "longitude": -89.46478,
        "region": null,
        "country": "El Salvador",
        "state": null,
        "county": null,
        "com_type": "N",
        "commod1": "Perlite",
        "commod2": null,
        "commod3": null,
        "oper_type": "Unknown",
        "dep_type": null,
        "prod_size": "N",
        "dev_stat": "Occurrence",
        "ore": null,
        "gangue": null,
        "other_matl": null,
        "orebody_fm": null,
        "work_type": null,
        "model": null,
        "alteration": null,
        "conc_proc": null,
        "names": null,
        "ore_ctrl": null,
        "reporter": "Page, Norman J.",
        "hrock_unit": null,
        "hrock_type": "Felsic Volcanic Rock",
        "arock_unit": null,
        "arock_type": null,
        "structure": null,
        "tectonic": null,
        "ref": "LORENZ, W., AND MULLER, P., 1982, PERLITE IN EL SALVADOR, CENTRAL AMERICA:  NEW MEXICO BUREAU OF MINES AND MINERAL RESOURCES CIRCULAR 182, P. 103-107CIMRI",
        "yfp_ba": null,
        "yr_fst_prd": null,
        "ylp_ba": null,
        "yr_lst_prd": null,
        "dy_ba": null,
        "disc_yr": null,
        "prod_yrs": null,
        "discr": null
      },
      "geometry": {
        "type": "Point",
        "coordinates": [
          -89.46478,
          14.14671
        ]
      }
    },
    {
      "type": "Feature",
      "properties": {
        "dep_id": 10057214,
        "url": "https://mrdata.usgs.gov/mrds/show-mrds.php?dep_id=10057214",
        "mrds_id": "TC01704",
        "mas_id": null,
        "site_name": "Yamabal",
        "latitude": 13.66757,
        "longitude": -88.18503,
        "region": null,
        "country": "El Salvador",
        "state": null,
        "county": null,
        "com_type": "N",
        "commod1": "Perlite",
        "commod2": null,
        "commod3": null,
        "oper_type": "Unknown",
        "dep_type": null,
        "prod_size": "N",
        "dev_stat": "Occurrence",
        "ore": null,
        "gangue": null,
        "other_matl": null,
        "orebody_fm": null,
        "work_type": null,
        "model": null,
        "alteration": null,
        "conc_proc": null,
        "names": null,
        "ore_ctrl": null,
        "reporter": "Page, Norman J.",
        "hrock_unit": null,
        "hrock_type": "Felsic Volcanic Rock",
        "arock_unit": null,
        "arock_type": null,
        "structure": null,
        "tectonic": null,
        "ref": "LORENZ, W., AND MULLER, P., 1982, PERLITE IN EL SALVADOR, CENTRAL AMERICA:  NEW MEXICO BUREAU OF MINES AND MINERAL RESOURCES CIRCULAR 182, P. 103-107CIMRI",
        "yfp_ba": null,
        "yr_fst_prd": null,
        "ylp_ba": null,
        "yr_lst_prd": null,
        "dy_ba": null,
        "disc_yr": null,
        "prod_yrs": null,
        "discr": null
      },
      "geometry": {
        "type": "Point",
        "coordinates": [
          -88.18503,
          13.66757
        ]
      }
    },
    {
      "type": "Feature",
      "properties": {
        "dep_id": 10057215,
        "url": "https://mrdata.usgs.gov/mrds/show-mrds.php?dep_id=10057215",
        "mrds_id": "TC01705",
        "mas_id": null,
        "site_name": "Cerro Pacho",
        "latitude": 13.93422,
        "longitude": -89.50006,
        "region": null,
        "country": "El Salvador",
        "state": null,
        "county": null,
        "com_type": "N",
        "commod1": "Perlite",
        "commod2": null,
        "commod3": null,
        "oper_type": "Unknown",
        "dep_type": null,
        "prod_size": "N",
        "dev_stat": "Occurrence",
        "ore": null,
        "gangue": null,
        "other_matl": null,
        "orebody_fm": null,
        "work_type": null,
        "model": null,
        "alteration": null,
        "conc_proc": null,
        "names": null,
        "ore_ctrl": null,
        "reporter": "Page, Norman J.",
        "hrock_unit": null,
        "hrock_type": "Felsic Volcanic Rock",
        "arock_unit": null,
        "arock_type": null,
        "structure": null,
        "tectonic": null,
        "ref": "LORENZ, W., AND MULLER, P., 1982, PERLITE IN EL SALVADOR, CENTRAL AMERICA:  NEW MEXICO BUREAU OF MINES AND MINERAL RESOURCES CIRCULAR 182, P. 103-107CIMRI",
        "yfp_ba": null,
        "yr_fst_prd": null,
        "ylp_ba": null,
        "yr_lst_prd": null,
        "dy_ba": null,
        "disc_yr": null,
        "prod_yrs": null,
        "discr": null
      },
      "geometry": {
        "type": "Point",
        "coordinates": [
          -89.50006,
          13.93422
        ]
      }
    },
    {
      "type": "Feature",
      "properties": {
        "dep_id": 10057216,
        "url": "https://mrdata.usgs.gov/mrds/show-mrds.php?dep_id=10057216",
        "mrds_id": "TC01706",
        "mas_id": null,
        "site_name": "Cerro Chacchacaste",
        "latitude": 13.75868,
        "longitude": -89.92979,
        "region": null,
        "country": "El Salvador",
        "state": null,
        "county": null,
        "com_type": "N",
        "commod1": "Perlite",
        "commod2": null,
        "commod3": null,
        "oper_type": "Unknown",
        "dep_type": null,
        "prod_size": "N",
        "dev_stat": "Occurrence",
        "ore": null,
        "gangue": null,
        "other_matl": null,
        "orebody_fm": null,
        "work_type": null,
        "model": null,
        "alteration": null,
        "conc_proc": null,
        "names": null,
        "ore_ctrl": null,
        "reporter": "Page, Norman J.",
        "hrock_unit": null,
        "hrock_type": "Felsic Volcanic Rock",
        "arock_unit": null,
        "arock_type": null,
        "structure": null,
        "tectonic": null,
        "ref": "LORENZ, W., AND MULLER, P., 1982, PERLITE IN EL SALVADOR, CENTRAL AMERICA:  NEW MEXICO BUREAU OF MINES AND MINERAL RESOURCES CIRCULAR 182, P. 103-107CIMRI",
        "yfp_ba": null,
        "yr_fst_prd": null,
        "ylp_ba": null,
        "yr_lst_prd": null,
        "dy_ba": null,
        "disc_yr": null,
        "prod_yrs": null,
        "discr": null
      },
      "geometry": {
        "type": "Point",
        "coordinates": [
          -89.92979,
          13.75868
        ]
      }
    },
    {
      "type": "Feature",
      "properties": {
        "dep_id": 10057217,
        "url": "https://mrdata.usgs.gov/mrds/show-mrds.php?dep_id=10057217",
        "mrds_id": "TC01707",
        "mas_id": null,
        "site_name": "El Salvador",
        "latitude": 13.66034,
        "longitude": -88.76393,
        "region": null,
        "country": "El Salvador",
        "state": null,
        "county": null,
        "com_type": "N",
        "commod1": "Perlite",
        "commod2": null,
        "commod3": null,
        "oper_type": "Unknown",
        "dep_type": null,
        "prod_size": "N",
        "dev_stat": "Occurrence",
        "ore": null,
        "gangue": null,
        "other_matl": null,
        "orebody_fm": null,
        "work_type": null,
        "model": null,
        "alteration": null,
        "conc_proc": null,
        "names": null,
        "ore_ctrl": null,
        "reporter": "Page, Norman J.",
        "hrock_unit": null,
        "hrock_type": "Felsic Volcanic Rock",
        "arock_unit": null,
        "arock_type": null,
        "structure": null,
        "tectonic": null,
        "ref": "LORENZ, W., AND MULLER, P., 1982, PERLITE IN EL SALVADOR, CENTRAL AMERICA:  NEW MEXICO BUREAU OF MINES AND MINERAL RESOURCES CIRCULAR 182, P. 103-107CIMRI",
        "yfp_ba": null,
        "yr_fst_prd": null,
        "ylp_ba": null,
        "yr_lst_prd": null,
        "dy_ba": null,
        "disc_yr": null,
        "prod_yrs": null,
        "discr": null
      },
      "geometry": {
        "type": "Point",
        "coordinates": [
          -88.76393,
          13.66034
        ]
      }
    },
    {
      "type": "Feature",
      "properties": {
        "dep_id": 10057218,
        "url": "https://mrdata.usgs.gov/mrds/show-mrds.php?dep_id=10057218",
        "mrds_id": "TC01708",
        "mas_id": null,
        "site_name": "Cerro Quemado",
        "latitude": 13.78646,
        "longitude": -88.97866,
        "region": null,
        "country": "El Salvador",
        "state": null,
        "county": null,
        "com_type": "N",
        "commod1": "Perlite",
        "commod2": null,
        "commod3": null,
        "oper_type": "Unknown",
        "dep_type": null,
        "prod_size": "N",
        "dev_stat": "Occurrence",
        "ore": null,
        "gangue": null,
        "other_matl": null,
        "orebody_fm": null,
        "work_type": null,
        "model": null,
        "alteration": null,
        "conc_proc": null,
        "names": null,
        "ore_ctrl": null,
        "reporter": "Page, Norman J.",
        "hrock_unit": null,
        "hrock_type": "Felsic Volcanic Rock",
        "arock_unit": null,
        "arock_type": null,
        "structure": null,
        "tectonic": null,
        "ref": "LORENZ, W., AND MULLER, P., 1982, PERLITE IN EL SALVADOR, CENTRAL AMERICA:  NEW MEXICO BUREAU OF MINES AND MINERAL RESOURCES CIRCULAR 182, P. 103-107CIMRI",
        "yfp_ba": null,
        "yr_fst_prd": null,
        "ylp_ba": null,
        "yr_lst_prd": null,
        "dy_ba": null,
        "disc_yr": null,
        "prod_yrs": null,
        "discr": null
      },
      "geometry": {
        "type": "Point",
        "coordinates": [
          -88.97866,
          13.78646
        ]
      }
    },
    {
      "type": "Feature",
      "properties": {
        "dep_id": 10057219,
        "url": "https://mrdata.usgs.gov/mrds/show-mrds.php?dep_id=10057219",
        "mrds_id": "TC01709",
        "mas_id": null,
        "site_name": "Cerro El Paraiso",
        "latitude": 13.77951,
        "longitude": -89.00061,
        "region": null,
        "country": "El Salvador",
        "state": null,
        "county": null,
        "com_type": "N",
        "commod1": "Perlite",
        "commod2": null,
        "commod3": null,
        "oper_type": "Unknown",
        "dep_type": null,
        "prod_size": "N",
        "dev_stat": "Occurrence",
        "ore": null,
        "gangue": null,
        "other_matl": null,
        "orebody_fm": null,
        "work_type": null,
        "model": null,
        "alteration": null,
        "conc_proc": null,
        "names": null,
        "ore_ctrl": null,
        "reporter": "Page, Norman J.",
        "hrock_unit": null,
        "hrock_type": "Felsic Volcanic Rock",
        "arock_unit": null,
        "arock_type": null,
        "structure": null,
        "tectonic": null,
        "ref": "LORENZ, W., AND MULLER, P., 1982, PERLITE IN EL SALVADOR, CENTRAL AMERICA:  NEW MEXICO BUREAU OF MINES AND MINERAL RESOURCES CIRCULAR 182, P. 103-107CIMRI",
        "yfp_ba": null,
        "yr_fst_prd": null,
        "ylp_ba": null,
        "yr_lst_prd": null,
        "dy_ba": null,
        "disc_yr": null,
        "prod_yrs": null,
        "discr": null
      },
      "geometry": {
        "type": "Point",
        "coordinates": [
          -89.00061,
          13.77951
        ]
      }
    },
    {
      "type": "Feature",
      "properties": {
        "dep_id": 10085938,
        "url": "https://mrdata.usgs.gov/mrds/show-mrds.php?dep_id=10085938",
        "mrds_id": "W701811",
        "mas_id": null,
        "site_name": "Divisadero Mine",
        "latitude": 13.60091,
        "longitude": -88.06002,
        "region": null,
        "country": "El Salvador",
        "state": "Morazan",
        "county": null,
        "com_type": "M",
        "commod1": "Gold, Silver",
        "commod2": null,
        "commod3": null,
        "oper_type": "Unknown",
        "dep_type": null,
        "prod_size": "Y",
        "dev_stat": "Past Producer",
        "ore": "Gold",
        "gangue": null,
        "other_matl": null,
        "orebody_fm": null,
        "work_type": null,
        "model": null,
        "alteration": null,
        "conc_proc": null,
        "names": "Divisadero, Matilde, San Francisco, Carolina, Protectora Veins",
        "ore_ctrl": null,
        "reporter": "Bliss, James D., Page, Norman J.",
        "hrock_unit": null,
        "hrock_type": "Volcanic Rock (Aphanitic)",
        "arock_unit": null,
        "arock_type": "Volcanic Rock (Aphanitic)",
        "structure": null,
        "tectonic": null,
        "ref": "INSTITUTO CENTROAMERICANO DE INVESTIGACION Y TECNOLOGIA INDUSTRIAL (ICAITI), 1970, MAPA METRALOGENETIO DE AMERICA CENTRAL; 1:2000000 & ESTUDIOS METALOGENETICOS DE AMERICA CENTRAL:  PUBLICIONES GEOLOGICAS DEL ICAITI NUMERO III, 76 P.ROBERTS, R.J., AND IRVING, E.M., 1957, MINERAL DEPOSITS OF CENTRAL AMERICA:  U.S. GEOLOGICAL SURVEY BULLETIN 1034, P. 191-192.CIMRIROBERTS AND IRVING, 1957.",
        "yfp_ba": null,
        "yr_fst_prd": null,
        "ylp_ba": null,
        "yr_lst_prd": null,
        "dy_ba": null,
        "disc_yr": null,
        "prod_yrs": null,
        "discr": null
      },
      "geometry": {
        "type": "Point",
        "coordinates": [
          -88.06002,
          13.60091
        ]
      }
    },
    {
      "type": "Feature",
      "properties": {
        "dep_id": 10085939,
        "url": "https://mrdata.usgs.gov/mrds/show-mrds.php?dep_id=10085939",
        "mrds_id": "W701814",
        "mas_id": null,
        "site_name": "El Dorado Mine",
        "latitude": 13.85089,
        "longitude": -88.80004,
        "region": null,
        "country": "El Salvador",
        "state": "Cabanas",
        "county": null,
        "com_type": "M",
        "commod1": "Silver, Gold",
        "commod2": null,
        "commod3": null,
        "oper_type": "Unknown",
        "dep_type": null,
        "prod_size": "N",
        "dev_stat": "Occurrence",
        "ore": "Gold, Pyrite",
        "gangue": null,
        "other_matl": null,
        "orebody_fm": null,
        "work_type": null,
        "model": null,
        "alteration": null,
        "conc_proc": null,
        "names": "Portillo Vein, Veins:  El Dorado, La Coyatera North, Nueva Experanza, Minita-Minita 3 Vein, Moreno Vein, Zancudo Vein.",
        "ore_ctrl": null,
        "reporter": "Bliss, James D., Page, Norman J.",
        "hrock_unit": null,
        "hrock_type": "Volcanic Rock (Aphanitic)",
        "arock_unit": null,
        "arock_type": "Volcanic Rock (Aphanitic)",
        "structure": null,
        "tectonic": null,
        "ref": "ANON. (1995).INSTITUTO CENTROAMERICANO DE INVESTIGACION Y TECNOLOGIA INDUSTRIAL (ICAITI), 1970, MAPA METRALOGENETIO DE AMERICA CENTRAL; 1:2000000 & ESTUDIOS METALOGENETICOS DE AMERICA CENTRAL:  PUBLICIONES GEOLOGICAS DEL ICAITI NUMERO III, 76 P.ROBERTS, R.J., AND IRVING, E.M., 1957, MINERAL DEPOSITS OF CENTRAL AMERICA:  U.S. GEOLOGICAL SURVEY BULLETIN 1034, P. 193.ANON., 1994, DRILLING ON EL DORADO PROJECT:  THE NORTHERN MINER, V. 80, NO. 36, P.6.ANON., 1995, MIRAGE, PARTNERS DRILL TESTING SALVADORAN PLAY:  THE NORTHERN MINER, FEBRUARY 20, 1995, V. 80, NO. 51, P. 20.ANON., 1995, PREFEASIBILITY STUDY EXPECTED FOR EL DORADO: THE NORTHERN MINER, V. 81, NO. 15, P. 12.CIMRI",
        "yfp_ba": null,
        "yr_fst_prd": null,
        "ylp_ba": null,
        "yr_lst_prd": null,
        "dy_ba": null,
        "disc_yr": null,
        "prod_yrs": null,
        "discr": null
      },
      "geometry": {
        "type": "Point",
        "coordinates": [
          -88.80004,
          13.85089
        ]
      }
    },
    {
      "type": "Feature",
      "properties": {
        "dep_id": 10085940,
        "url": "https://mrdata.usgs.gov/mrds/show-mrds.php?dep_id=10085940",
        "mrds_id": "W701815",
        "mas_id": null,
        "site_name": "Monte Mayor Mine",
        "latitude": 13.7009,
        "longitude": -87.97002,
        "region": null,
        "country": "El Salvador",
        "state": "Morazan",
        "county": null,
        "com_type": "M",
        "commod1": "Gold, Silver",
        "commod2": null,
        "commod3": null,
        "oper_type": "Unknown",
        "dep_type": null,
        "prod_size": "Y",
        "dev_stat": "Past Producer",
        "ore": "Gold",
        "gangue": null,
        "other_matl": null,
        "orebody_fm": null,
        "work_type": null,
        "model": null,
        "alteration": null,
        "conc_proc": null,
        "names": "Las Tunas Veins, Monte Mayor, Santa Gertrudia, Carao, Tempisque, Banadeto",
        "ore_ctrl": null,
        "reporter": "Bliss, James D., Page, Norman J.",
        "hrock_unit": null,
        "hrock_type": "Volcanic Rock (Aphanitic)",
        "arock_unit": null,
        "arock_type": "Volcanic Rock (Aphanitic)",
        "structure": null,
        "tectonic": null,
        "ref": "INSTITUTO CENTROAMERICANO DE INVESTIGACION Y TECNOLOGIA INDUSTRIAL (ICAITI), 1970, MAPA METRALOGENETIO DE AMERICA CENTRAL; 1:2000000 & ESTUDIOS METALOGENETICOS DE AMERICA CENTRAL:  PUBLICIONES GEOLOGICAS DEL ICAITI NUMERO III, 76 P.ROBERTS, R.J., AND IRVING, E.M., 1957, MINERAL DEPOSITS OF CENTRAL AMERICA:  U.S. GEOLOGICAL SURVEY BULLETIN 1034, P. 192.CIMRIROBERTS AND IRVING, 1957.",
        "yfp_ba": null,
        "yr_fst_prd": null,
        "ylp_ba": null,
        "yr_lst_prd": null,
        "dy_ba": null,
        "disc_yr": null,
        "prod_yrs": null,
        "discr": null
      },
      "geometry": {
        "type": "Point",
        "coordinates": [
          -87.97002,
          13.7009
        ]
      }
    },
    {
      "type": "Feature",
      "properties": {
        "dep_id": 10085941,
        "url": "https://mrdata.usgs.gov/mrds/show-mrds.php?dep_id=10085941",
        "mrds_id": "W701816",
        "mas_id": null,
        "site_name": "Monte Cristo Mine",
        "latitude": 13.60091,
        "longitude": -88.07002,
        "region": null,
        "country": "El Salvador",
        "state": "Morazan",
        "county": null,
        "com_type": "M",
        "commod1": "Gold, Silver",
        "commod2": null,
        "commod3": null,
        "oper_type": "Unknown",
        "dep_type": null,
        "prod_size": "Y",
        "dev_stat": "Past Producer",
        "ore": "Gold, Pyrite, Sphalerite",
        "gangue": "Quartz",
        "other_matl": null,
        "orebody_fm": null,
        "work_type": "Underground",
        "model": null,
        "alteration": null,
        "conc_proc": null,
        "names": null,
        "ore_ctrl": null,
        "reporter": "Bliss, James D., Page, Norman J.",
        "hrock_unit": null,
        "hrock_type": "Volcanic Rock (Aphanitic)",
        "arock_unit": null,
        "arock_type": "Volcanic Rock (Aphanitic)",
        "structure": null,
        "tectonic": null,
        "ref": "INSTITUTO CENTROAMERICANO DE INVESTIGACION Y TECNOLOGIA INDUSTRIAL (ICAITI), 1970, MAPA METRALOGENETIO DE AMERICA CENTRAL; 1:2000000 & ESTUDIOS METALOGENETICOS DE AMERICA CENTRAL:  PUBLICIONES GEOLOGICAS DEL ICAITI NUMERO III, 76 P.ROBERTS, R.J., AND IRVING, E.M., 1957, MINERAL DEPOSITS OF CENTRAL AMERICA:  U.S. GEOLOGICAL SURVEY BULLETIN 1034, P. 193.SWANQUIST, G.A., 1941, EL SALVADOR:  ENGINEERING AND MINING JOURNAL, AUGUST 1941, P. 155.CIMRIROBERTS AND IRVING, 1957; SWANQUIST, 1941.",
        "yfp_ba": null,
        "yr_fst_prd": 1933.0,
        "ylp_ba": null,
        "yr_lst_prd": null,
        "dy_ba": null,
        "disc_yr": null,
        "prod_yrs": null,
        "discr": null
      },
      "geometry": {
        "type": "Point",
        "coordinates": [
          -88.07002,
          13.60091
        ]
      }
    },
    {
      "type": "Feature",
      "properties": {
        "dep_id": 10085942,
        "url": "https://mrdata.usgs.gov/mrds/show-mrds.php?dep_id=10085942",
        "mrds_id": "W701818",
        "mas_id": null,
        "site_name": "San Juan Mine",
        "latitude": 14.29087,
        "longitude": -89.37006,
        "region": null,
        "country": "El Salvador",
        "state": "Santa Ana",
        "county": null,
        "com_type": "M",
        "commod1": "Lead, Zinc, Silver",
        "commod2": null,
        "commod3": null,
        "oper_type": "Unknown",
        "dep_type": null,
        "prod_size": "Y",
        "dev_stat": "Past Producer",
        "ore": "Galena, Pyrite, Sphalerite",
        "gangue": null,
        "other_matl": null,
        "orebody_fm": null,
        "work_type": "Underground",
        "model": "60: Skarn Zn-Pb",
        "alteration": null,
        "conc_proc": null,
        "names": null,
        "ore_ctrl": null,
        "reporter": "Bliss, James D., Page, Norman J.",
        "hrock_unit": null,
        "hrock_type": "Skarn (Tactite),Limestone",
        "arock_unit": null,
        "arock_type": "Diorite",
        "structure": null,
        "tectonic": null,
        "ref": "INSTITUTO CENTROAMERICANO DE INVESTIGACION Y TECNOLOGIA INDUSTRIAL (ICAITI), 1970, MAPA METRALOGENETIO DE AMERICA CENTRAL; 1:2000000 & ESTUDIOS METALOGENETICOS DE AMERICA CENTRAL:  PUBLICIONES GEOLOGICAS DEL ICAITI NUMERO III, 76 P.ROBERTS, R.J., AND IRVING, E.M., 1957, MINERAL DEPOSITS OF CENTRAL AMERICA:  U.S. GEOLOGICAL SURVEY BULLETIN 1034, P. 74-76.CIMRIROBERTS AND IRVING, 1957.",
        "yfp_ba": null,
        "yr_fst_prd": 1917.0,
        "ylp_ba": null,
        "yr_lst_prd": null,
        "dy_ba": null,
        "disc_yr": null,
        "prod_yrs": "APPEARS TO HAVE BEEN IN OPERATION 1917 TO 1931 OR 32, PRODUCTION BEGAN AGAIN IN 1951",
        "discr": null
      },
      "geometry": {
        "type": "Point",
        "coordinates": [
          -89.37006,
          14.29087
        ]
      }
    },
    {
      "type": "Feature",
      "properties": {
        "dep_id": 10085943,
        "url": "https://mrdata.usgs.gov/mrds/show-mrds.php?dep_id=10085943",
        "mrds_id": "W701819",
        "mas_id": null,
        "site_name": "San Sebastian Mine",
        "latitude": 13.6509,
        "longitude": -87.93002,
        "region": null,
        "country": "El Salvador",
        "state": "La Union",
        "county": null,
        "com_type": "M",
        "commod1": "Gold, Silver",
        "commod2": null,
        "commod3": null,
        "oper_type": "Unknown",
        "dep_type": null,
        "prod_size": "Y",
        "dev_stat": "Past Producer",
        "ore": "Bornite, Calaverite, Chalcocite, Chalcopyrite, Gold, Marcasite, Molybdenite, Pyrite, Pyrolusite, Pyrrhotite",
        "gangue": "Barite, Calcite, Chlorite, Epidote, Gypsum, Quartz",
        "other_matl": null,
        "orebody_fm": null,
        "work_type": "Underground",
        "model": null,
        "alteration": "Silicification, Propylization",
        "conc_proc": null,
        "names": null,
        "ore_ctrl": null,
        "reporter": "Bliss, James D., Page, Norman J.",
        "hrock_unit": null,
        "hrock_type": "Trachyte,Basalt",
        "arock_unit": null,
        "arock_type": "Quartz Monzonite",
        "structure": null,
        "tectonic": null,
        "ref": "INSTITUTO CENTROAMERICANO DE INVESTIGACION Y TECNOLOGIA INDUSTRIAL (ICAITI), 1970, MAPA METRALOGENETIO DE AMERICA CENTRAL; 1:2000000 & ESTUDIOS METALOGENETICOS DE AMERICA CENTRAL:  PUBLICIONES GEOLOGICAS DEL ICAITI NUMERO III, 76 P.ROBERTS, R.J., AND IRVING, E.M., 1957, MINERAL DEPOSITS OF CENTRAL AMERICA:  U.S. GEOLOGICAL SURVEY BULLETIN 1034, P. 191.WUENSCH, C.E., 1917, GEOLOGY OF THE SAN SEBASTIAN MINE, SALVADOR:  MINING AND SCIENTIFIC PRESS, SEPT. 8, 1917, P. 345-350.CIMRIROBERTS AND IRVING (1957); WUENSCH (1917).",
        "yfp_ba": null,
        "yr_fst_prd": null,
        "ylp_ba": null,
        "yr_lst_prd": null,
        "dy_ba": null,
        "disc_yr": 1673.0,
        "prod_yrs": null,
        "discr": null
      },
      "geometry": {
        "type": "Point",
        "coordinates": [
          -87.93002,
          13.6509
        ]
      }
    },
    {
      "type": "Feature",
      "properties": {
        "dep_id": 10093903,
        "url": "https://mrdata.usgs.gov/mrds/show-mrds.php?dep_id=10093903",
        "mrds_id": "W701813",
        "mas_id": null,
        "site_name": "Laguna Alegria",
        "latitude": 13.49091,
        "longitude": -88.49003,
        "region": null,
        "country": "El Salvador",
        "state": "Usulutan",
        "county": null,
        "com_type": "N",
        "commod1": "Sulfur",
        "commod2": null,
        "commod3": null,
        "oper_type": "Unknown",
        "dep_type": null,
        "prod_size": "N",
        "dev_stat": "Occurrence",
        "ore": "Sulfur",
        "gangue": null,
        "other_matl": null,
        "orebody_fm": null,
        "work_type": null,
        "model": null,
        "alteration": null,
        "conc_proc": null,
        "names": null,
        "ore_ctrl": null,
        "reporter": "Bliss, James D.",
        "hrock_unit": null,
        "hrock_type": "Volcanic Rock (Aphanitic)",
        "arock_unit": null,
        "arock_type": "Volcanic Rock (Aphanitic)",
        "structure": null,
        "tectonic": null,
        "ref": "INSTITUTO CENTROAMERICANO DE INVESTIGACION Y TECNOLOGIA INDUSTRIAL (ICAITI), 1970, MAPA METRALOGENETIO DE AMERICA CENTRAL; 1:2000000 & ESTUDIOS METALOGENETICOS DE AMERICA CENTRAL:  PUBLICIONES GEOLOGICAS DEL ICAITI NUMERO III, 76 P",
        "yfp_ba": null,
        "yr_fst_prd": null,
        "ylp_ba": null,
        "yr_lst_prd": null,
        "dy_ba": null,
        "disc_yr": null,
        "prod_yrs": null,
        "discr": null
      },
      "geometry": {
        "type": "Point",
        "coordinates": [
          -88.49003,
          13.49091
        ]
      }
    },
    {
      "type": "Feature",
      "properties": {
        "dep_id": 10106485,
        "url": "https://mrdata.usgs.gov/mrds/show-mrds.php?dep_id=10106485",
        "mrds_id": "W701812",
        "mas_id": null,
        "site_name": "Hormiguero Mine",
        "latitude": 13.53091,
        "longitude": -88.06002,
        "region": null,
        "country": "El Salvador",
        "state": "San Miguel",
        "county": null,
        "com_type": "M",
        "commod1": "Gold, Silver",
        "commod2": null,
        "commod3": null,
        "oper_type": "Unknown",
        "dep_type": null,
        "prod_size": "Y",
        "dev_stat": "Past Producer",
        "ore": "Chalcopyrite, Galena, Gold, Malachite, Pyrite, Sphalerite",
        "gangue": "Quartz",
        "other_matl": null,
        "orebody_fm": null,
        "work_type": "Underground",
        "model": null,
        "alteration": null,
        "conc_proc": null,
        "names": "Gallardo, Homiguero, And Guadalupe Veins",
        "ore_ctrl": null,
        "reporter": "Page, Norman J., Bliss, James D.",
        "hrock_unit": null,
        "hrock_type": "Volcanic Rock (Aphanitic)",
        "arock_unit": null,
        "arock_type": "Volcanic Rock (Aphanitic)",
        "structure": null,
        "tectonic": null,
        "ref": "INSTITUTO CENTROAMERICANO DE INVESTIGACION Y TECNOLOGIA INDUSTRIAL (ICAITI), 1970, MAPA METRALOGENETIO DE AMERICA CENTRAL; 1:2000000 & ESTUDIOS METALOGENETICOS DE AMERICA CENTRAL:  PUBLICIONES GEOLOGICAS DEL ICAITI NUMERO III, 76 P.ROBERTS, R.J., AND IRVING, E.M., 1957, MINERAL DEPOSITS OF CENTRAL AMERICA:  U.S. GEOLOGICAL SURVEY BULLETIN 1034, P. 192.CIMRIROBERTS AND IRVING, 1957.",
        "yfp_ba": null,
        "yr_fst_prd": null,
        "ylp_ba": null,
        "yr_lst_prd": null,
        "dy_ba": null,
        "disc_yr": null,
        "prod_yrs": null,
        "discr": null
      },
      "geometry": {
        "type": "Point",
        "coordinates": [
          -88.06002,
          13.53091
        ]
      }
    },
    {
      "type": "Feature",
      "properties": {
        "dep_id": 10106486,
        "url": "https://mrdata.usgs.gov/mrds/show-mrds.php?dep_id=10106486",
        "mrds_id": "W701817",
        "mas_id": null,
        "site_name": "Potosi Mine",
        "latitude": 13.7009,
        "longitude": -88.34003,
        "region": null,
        "country": "El Salvador",
        "state": "San Miguel",
        "county": null,
        "com_type": "M",
        "commod1": "Gold, Silver",
        "commod2": null,
        "commod3": null,
        "oper_type": "Unknown",
        "dep_type": null,
        "prod_size": "Y",
        "dev_stat": "Past Producer",
        "ore": "Gold",
        "gangue": null,
        "other_matl": null,
        "orebody_fm": null,
        "work_type": null,
        "model": null,
        "alteration": null,
        "conc_proc": null,
        "names": null,
        "ore_ctrl": null,
        "reporter": "Bliss, James D., Page, Norman J.",
        "hrock_unit": null,
        "hrock_type": "Rhyolite",
        "arock_unit": null,
        "arock_type": "Volcanic Rock (Aphanitic)",
        "structure": null,
        "tectonic": null,
        "ref": "INSTITUTO CENTROAMERICANO DE INVESTIGACION Y TECNOLOGIA INDUSTRIAL (ICAITI), 1970, MAPA METRALOGENETIO DE AMERICA CENTRAL; 1:2000000 & ESTUDIOS METALOGENETICOS DE AMERICA CENTRAL:  PUBLICIONES GEOLOGICAS DEL ICAITI NUMERO III, 76 P.ROBERTS, R.J., AND IRVING, E.M., 1957, MINERAL DEPOSITS OF CENTRAL AMERICA:  U.S. GEOLOGICAL SURVEY BULLETIN 1034, P. 193.SWANQUIST, G.A., 1941, EL SALVADOR:  ENGINEERING AND MINING JOURNAL, AUGUST 1941, P. 155.CIMRISWANQUIST (1941).",
        "yfp_ba": null,
        "yr_fst_prd": null,
        "ylp_ba": null,
        "yr_lst_prd": null,
        "dy_ba": null,
        "disc_yr": null,
        "prod_yrs": null,
        "discr": null
      },
      "geometry": {
        "type": "Point",
        "coordinates": [
          -88.34003,
          13.7009
        ]
      }
    }
  ]
}